local_db/__init__.py
local_db/create_db.py
local_db/query_db.py
local_db_lasdot-0.0.2.dist-info/LICENSE
local_db_lasdot-0.0.2.dist-info/METADATA
local_db_lasdot-0.0.2.dist-info/WHEEL
local_db_lasdot-0.0.2.dist-info/top_level.txt
local_db_lasdot-0.0.2.dist-info/RECORD
