Metadata-Version: 2.1
Name: local-db-lasdot
Version: 0.0.2
Summary: light weight package for populating mongo database and query it with energy data
Home-page: https://github.com/Leko25/LocalDb.git
Author: Kelechi Ogudu
Author-email: icheleck25@gmail.com
License: UNKNOWN
Platform: UNKNOWN
Classifier: Programming Language :: Python :: 3
Classifier: License :: OSI Approved :: MIT License
Classifier: Operating System :: OS Independent
Requires-Python: >=3.5
